maxoptics/__init__.py
maxoptics/__main__.py
maxoptics/config.py
maxoptics/macros.py
maxoptics/sdk.py
maxoptics/core/JSasync.py
maxoptics/core/TaskFile.py
maxoptics/core/__init__.py
maxoptics/core/abc.py
maxoptics/core/error.py
maxoptics/core/logger.py
maxoptics/core/base/BaseCell.py
maxoptics/core/base/BaseContainer.py
maxoptics/core/base/BaseDataCls.py
maxoptics/core/base/Runner.py
maxoptics/core/base/__init__.py
maxoptics/core/base/task.py
maxoptics/core/component/__init__.py
maxoptics/core/component/base/Attrs.py
maxoptics/core/component/base/Component.py
maxoptics/core/component/base/__init__.py
maxoptics/core/component/base/base.py
maxoptics/core/gdstools/GdsMaterial.py
maxoptics/core/gdstools/GdsParser.py
maxoptics/core/gdstools/GdsTypes.py
maxoptics/core/gdstools/PdkParser.py
maxoptics/core/gdstools/ProgressBar.py
maxoptics/core/gdstools/__init__.py
maxoptics/core/gdstools/structures.py
maxoptics/core/plot/GeoBase.py
maxoptics/core/plot/PolygonLike.py
maxoptics/core/plot/__init__.py
maxoptics/core/plot/draw_line.py
maxoptics/core/plot/draw_polygons.py
maxoptics/core/plot/heatmap.py
maxoptics/core/project/Project.py
maxoptics/core/project/ProjectBase.py
maxoptics/core/project/__init__.py
maxoptics/core/project/utils.py
maxoptics/core/utils/__init__.py
maxoptics/core/utils/attach_port.py
maxoptics/core/utils/currying.py
maxoptics/core/utils/configtools/__init__.py
maxoptics/core/utils/configtools/set.py
maxoptics/core/utils/configtools/set_save_dir.py
maxoptics/core/utils/configtools/set_url.py
maxoptics/core/utils/configtools/update.py
maxoptics/core/utils/constraints/ComponentScopeSyncer.py
maxoptics/core/utils/constraints/ProjectScopeSyncer.py
maxoptics/core/utils/constraints/__init__.py
maxoptics/core/utils/constraints/base.py
maxoptics/core/visualizer/__init__.py
maxoptics/core/visualizer/common.py
maxoptics/core/visualizer/utils.py
maxoptics/examples/__init__.py
maxoptics/examples/fast_demo/EME_PSR.py
maxoptics/examples/fast_demo/EME_SSC.py
maxoptics_cloud_sdk-0.9.2.623.937.dist-info/METADATA
maxoptics_cloud_sdk-0.9.2.623.937.dist-info/WHEEL
maxoptics_cloud_sdk-0.9.2.623.937.dist-info/top_level.txt
maxoptics_cloud_sdk-0.9.2.623.937.dist-info/RECORD
